rigel/__init__.py
rigel/cli.py
rigel/exceptions.py
rigel/files/__init__.py
rigel/files/assets/Rigelfile
rigel/files/assets/templates/Dockerfile.j2
rigel/files/assets/templates/config.j2
rigel/files/assets/templates/entrypoint.j2
rigel/files/creator.py
rigel/files/decoder.py
rigel/files/loader.py
rigel/files/renderer.py
rigel/models/__init__.py
rigel/models/docker.py
rigel/models/plugin.py
rigel/models/rigelfile.py
rigel/models/simulation.py
rigel/plugins/__init__.py
rigel/plugins/installer.py
rigel/plugins/loader.py
rigel/plugins/plugin.py
rigel/py.typed
rigel-0.2.22.dist-info/entry_points.txt
rigel-0.2.22.dist-info/LICENSE.md
rigel-0.2.22.dist-info/WHEEL
rigel-0.2.22.dist-info/METADATA
rigel-0.2.22.dist-info/RECORD
