Metadata-Version: 2.1
Name: rigel
Version: 0.2.22
Summary: Containerize and deploy your ROS application using Docker.
Home-page: https://github.com/rigel-ros/rigel
License: MIT
Keywords: docker,ros,cloud,robotics
Author: Pedro Miguel Melo
Author-email: pedro.m.melo@inesctec.pt
Maintainer: Pedro Miguel Melo
Maintainer-email: pedro.m.melo@inesctec.pt
Requires-Python: >=3.8,<4.0
Classifier: Intended Audience :: Developers
Classifier: License :: OSI Approved :: MIT License
Classifier: Operating System :: POSIX
Classifier: Programming Language :: Python :: 3
Classifier: Programming Language :: Python :: 3 :: Only
Classifier: Programming Language :: Python :: 3.10
Classifier: Programming Language :: Python :: 3.8
Classifier: Programming Language :: Python :: 3.9
Requires-Dist: Jinja2 (>=3.0.3,<4.0.0)
Requires-Dist: PyYAML (>=6.0,<7.0)
Requires-Dist: click (>=8.0.3,<9.0.0)
Requires-Dist: pydantic (>=1.9.0,<2.0.0)
Requires-Dist: rich (>=11.2.0,<12.0.0)
Requires-Dist: rigel-local-simulation-plugin (>=0.1.0,<0.2.0)
Requires-Dist: rigel-registry-plugin (>=0.1.6,<0.2.0)
Requires-Dist: rigelcore (>=0.1.19,<0.2.0)
Project-URL: Repository, https://github.com/rigel-ros/rigel
